<xml>
<game id="1">
<type>guessPic</type>
<questions>2</questions>
<question>
<qtext>Which Celebrity Is This?</qtext>
<qpic>http://www.womenlargejaw.com/sites/www.womenlargejaw.com/files/women/Princess_1225109841.jpg</qpic>
</question>
<option id="1">
<text>Kate Middleton</text>
<pic></pic>
</option>
<option id="2">
<text>Pippa Middleton</text>
<pic></pic>
</option>
<option id="3">
<text>Queen Maxima</text>
<pic></pic>
</option>
<option id="4">
<text>Victoria of Sweden</text>
<pic></pic>
</option>
<answer1>
<answerok>4</answerok>
<messageok>Correct!!!</messageok>
<messageko>Woof, incorrect!!!</messageko>
<points>10</points>
<timebonus>2</timebonus>
<extrabonus>5</extrabonus>
</answer1>
</game>
<game id="2">
<type>guessPic</type>
<question>
<qtext>Which Celebrity Is This?</qtext>
<qpic>http://espndeportes-assets.espn.go.com/2003/photos2012/1016/messi_576.jpg</qpic>
</question>
<option id="1">
<text>Cristiano Ronaldo</text>
<pic></pic>
</option>
<option id="2">
<text>Lionel Messi</text>
<pic></pic>
</option>
<option id="3">
<text>Luis Figo</text>
<pic></pic>
</option>
<option id="4">
<text>Michael Ballack</text>
<pic></pic>
</option>
<answer2>
<answerok>2</answerok>
<messageok>Correct!!!</messageok>
<messageko>Woof, incorrect!!!</messageko>
<points>10</points>
<timebonus>2</timebonus>
<extrabonus>5</extrabonus>
</answer2>
</game>

<game id="3">
<type>guessPic</type>
<question>
<qtext>Which Celebrity Is This?</qtext>
<qpic>http://www.bonlook.com/sites/default/files/John%20Hamm.JPG</qpic>
</question>
<option id="1">
<text>Pep Guardiola</text>
<pic></pic>
</option>
<option id="2">
<text>Tom Cruise</text>
<pic></pic>
</option>
<option id="3">
<text>Robert Redford</text>
<pic></pic>
</option>
<option id="4">
<text>Jon Hamm</text>
<pic></pic>
</option>
<answer3>
<answerok>4</answerok>
<messageok>Correct!!!</messageok>
<messageko>Woof, incorrect!!!</messageko>
<points>10</points>
<timebonus>2</timebonus>
<extrabonus>5</extrabonus>
</answer3>
</game>


<game id="4">
<type>guessPic</type>
<question>
<qtext>Which Celebrity Is This?</qtext>
<qpic>https://encrypted-tbn1.gstatic.com/images?q=tbn:ANd9GcQcNirwSJ2kKIddWl1_gMQDyBNRE6XZl1_hqM0YXAuqSzMgOjeVCA</qpic>
</question>
<option id="1">
<text>Sharon Stone</text>
<pic></pic>
</option>
<option id="2">
<text>Scarlett Johansson</text>
<pic></pic>
</option>
<option id="3">
<text>Kate Upton</text>
<pic></pic>
</option>
<option id="4">
<text>Erin Andrews</text>
<pic></pic>
</option>
<answer4>
<answerok>3</answerok>
<messageok>Correct!!!</messageok>
<messageko>Woof, incorrect!!!</messageko>
<points>10</points>
<timebonus>2</timebonus>
<extrabonus>5</extrabonus>
</answer4>
</game>

<game id="5">
<type>guessPic</type>
<question>
<qtext>Which Celebrity Is This?</qtext>
<qpic>http://img2.timeinc.net/people/i/2009/database/katyperry/katy_perry125.jpg</qpic>
</question>
<option id="1">
<text>Katy Perry</text>
<pic></pic>
</option>
<option id="2">
<text>Selena Gomez</text>
<pic></pic>
</option>
<option id="3">
<text>Taylor Swift</text>
<pic></pic>
</option>
<option id="4">
<text>Kelly Clarkson</text>
<pic></pic>
</option>
<answer5>
<answerok>1</answerok>
<messageok>Correct!!!</messageok>
<messageko>Woof, incorrect!!!</messageko>
<points>10</points>
<timebonus>2</timebonus>
<extrabonus>5</extrabonus>
</answer5>
</game>


<game id="6">
<type>guessPic</type>
<question>
<qtext>Which Celebrity Is This?</qtext>
<qpic>http://www.nobelprize.org/nobel_prizes/peace/laureates/1964/king.jpg</qpic>
</question>
<option id="1">
<text>Kofi Annan</text>
<pic></pic>
</option>
<option id="2">
<text>Nelson Mandela</text>
<pic></pic>
</option>
<option id="3">
<text>Mahatma Gandhi</text>
<pic></pic>
</option>
<option id="4">
<text>Martin Luther King</text>
<pic></pic>
</option>
<answer6>
<answerok>4</answerok>
<messageok>Correct!!!</messageok>
<messageko>Woof, incorrect!!!</messageko>
<points>10</points>
<timebonus>2</timebonus>
<extrabonus>5</extrabonus>
</answer6>
</game>

<game id="7">
<type>guessPic</type>
<question>
<qtext>Which Celebrity Is This?</qtext>
<qpic>http://img2.timeinc.net/people/i/2007/database/heidiklum/heidiklum125.jpg</qpic>
</question>
<option id="1">
<text>Jennifer Garner</text>
<pic></pic>
</option>
<option id="2">
<text>Jennifer Lopez</text>
<pic></pic>
</option>
<option id="3">
<text>Jessica Alba</text>
<pic></pic>
</option>
<option id="4">
<text>Heidi Klum</text>
<pic></pic>
</option>
<answer7>
<answerok>4</answerok>
<messageok>Correct!!!</messageok>
<messageko>Woof, incorrect!!!</messageko>
<points>10</points>
<timebonus>2</timebonus>
<extrabonus>5</extrabonus>
</answer7>
</game>


<game id="8">
<type>guessPic</type>
<question>
<qtext>Which Celebrity Is This?</qtext>
<qpic>http://lakers.topbuzz.com/gallery/d/4288-2/kareem-p1_kareem_abdul_jabbar_si.jpg</qpic>
</question>
<option id="1">
<text>Oscar Robertson</text>
<pic></pic>
</option>
<option id="2">
<text>Kareem Abdul-Jabbar</text>
<pic></pic>
</option>
<option id="3">
<text>Wilt Chamberlain</text>
<pic></pic>
</option>
<option id="4">
<text>Bill Russell</text>
<pic></pic>
</option>
<answer8>
<answerok>2</answerok>
<messageok>Correct!!!</messageok>
<messageko>Woof, incorrect!!!</messageko>
<points>10</points>
<timebonus>2</timebonus>
<extrabonus>5</extrabonus>
</answer8>
</game>

<game id="9">
<type>guessPic</type>
<question>
<qtext>Which Celebrity Is This?</qtext>
<qpic>http://img2.timeinc.net/people/i/2006/celebdatabase/angelinajolie/angelina_jolie1a_125x125.jpg</qpic>
</question>
<option id="1">
<text>Courteney Cox</text>
<pic></pic>
</option>
<option id="2">
<text>Kim Kardashian</text>
<pic></pic>
</option>
<option id="3">
<text>Angelina Jolie</text>
<pic></pic>
</option>
<option id="4">
<text>Megan Fox</text>
<pic></pic>
</option>
<answer9>
<answerok>3</answerok>
<messageok>Correct!!!</messageok>
<messageko>Woof, incorrect!!!</messageko>
<points>10</points>
<timebonus>2</timebonus>
<extrabonus>5</extrabonus>
</answer9>
</game>

<game id="10">
<type>guessPic</type>
<question>
<qtext>Which Celebrity Is This?</qtext>
<qpic>http://img2.timeinc.net/people/i/2011/database/111010/ben-affleck-125.jpg</qpic>
</question>
<option id="1">
<text>Matt LeBlanc</text>
<pic></pic>
</option>
<option id="2">
<text>Matthew Perry</text>
<pic></pic>
</option>
<option id="3">
<text>George Clooney</text>
<pic></pic>
</option>
<option id="4">
<text>Ben Affleck</text>
<pic></pic>
</option>
<answer10>
<answerok>4</answerok>
<messageok>Correct!!!</messageok>
<messageko>Woof, incorrect!!!</messageko>
<points>10</points>
<timebonus>2</timebonus>
<extrabonus>5</extrabonus>
</answer10>
</game>







</xml>